themekitcli/__init__.py
themekitcli/__main__.py
themekitcli/logger.py
themekitcli/menus.py
themekit_cli-1.0.0.dist-info/METADATA
themekit_cli-1.0.0.dist-info/WHEEL
themekit_cli-1.0.0.dist-info/entry_points.txt
themekit_cli-1.0.0.dist-info/top_level.txt
themekit_cli-1.0.0.dist-info/zip-safe
themekit_cli-1.0.0.dist-info/RECORD
